arpa2.wsgi-0.5.1-py3.7-nspkg.pth
arpa2/wsgi/byoid/__init__.py
arpa2/wsgi/byoid/wsgisasl.py
arpa2/wsgi/byoid/wsgiuser.py
arpa2.wsgi-0.5.1.dist-info/METADATA
arpa2.wsgi-0.5.1.dist-info/WHEEL
arpa2.wsgi-0.5.1.dist-info/namespace_packages.txt
arpa2.wsgi-0.5.1.dist-info/top_level.txt
arpa2.wsgi-0.5.1.dist-info/RECORD
