Metadata-Version: 2.1
Name: arpa2.wsgi
Version: 0.5.1
Summary: WSGI Middleware to "Bring Your Own IDentity" to a web server
Home-page: https://github.com/arpa2/wsgi-middleware
Author: Rick van Rein (ARPA2 developer)
Author-email: rick@openfortress.nl
License: UNKNOWN
Platform: UNKNOWN
